[
  {
    "PigBankRow": {
      "ID": 1,
      "ActivityId": 0,
      "Type": 1,
      "ShopId": 10001,
      "BaseValue": 80,
      "InitValue": 160,
      "MaxValue": 320,
      "LayerAdd": 10,
      "TimeLimit": 24,
      "TitleId": 482,
      "DescId": [
        486,
        487,
        490,
        491
      ],
      "ResId": [
        1,
        1,
        1,
        1
      ]
    }
  },
  {
    "PigBankRow": {
      "ID": 2,
      "ActivityId": 0,
      "Type": 1,
      "ShopId": 10002,
      "BaseValue": 500,
      "InitValue": 1000,
      "MaxValue": 2000,
      "LayerAdd": 25,
      "TimeLimit": 48,
      "TitleId": 483,
      "DescId": [
        486,
        487,
        490,
        491
      ],
      "ResId": [
        2,
        2,
        2,
        2
      ]
    }
  },
  {
    "PigBankRow": {
      "ID": 3,
      "ActivityId": 0,
      "Type": 1,
      "ShopId": 10003,
      "BaseValue": 1200,
      "InitValue": 2400,
      "MaxValue": 4800,
      "LayerAdd": 50,
      "TimeLimit": 72,
      "TitleId": 484,
      "DescId": [
        486,
        487,
        490,
        491
      ],
      "ResId": [
        3,
        3,
        3,
        3
      ]
    }
  },
  {
    "PigBankRow": {
      "ID": 4,
      "ActivityId": 0,
      "Type": 1,
      "ShopId": 10004,
      "BaseValue": 2500,
      "InitValue": 5000,
      "MaxValue": 10000,
      "LayerAdd": 100,
      "TimeLimit": 72,
      "TitleId": 485,
      "DescId": [
        486,
        487,
        490,
        491
      ],
      "ResId": [
        4,
        4,
        4,
        4
      ]
    }
  },
  {
    "PigBankRow": {
      "ID": 5,
      "ActivityId": 11,
      "Type": 2,
      "ShopId": 10101,
      "BaseValue": 200,
      "InitValue": 400,
      "MaxValue": 800,
      "LayerAdd": 50,
      "TimeLimit": 8,
      "TitleId": 834,
      "DescId": [
        486,
        487,
        490,
        491
      ],
      "ResId": [
        1,
        1,
        1,
        1
      ]
    }
  },
  {
    "PigBankRow": {
      "ID": 11,
      "ActivityId": 20230101,
      "Type": 1,
      "ShopId": 10001,
      "BaseValue": 80,
      "InitValue": 160,
      "MaxValue": 320,
      "LayerAdd": 10,
      "TimeLimit": 24,
      "TitleId": 1650,
      "DescId": [
        1654,
        1655,
        1656,
        1657
      ],
      "ResId": [
        1,
        1,
        1,
        1
      ]
    }
  },
  {
    "PigBankRow": {
      "ID": 12,
      "ActivityId": 20230101,
      "Type": 1,
      "ShopId": 10002,
      "BaseValue": 500,
      "InitValue": 1000,
      "MaxValue": 2000,
      "LayerAdd": 25,
      "TimeLimit": 48,
      "TitleId": 1651,
      "DescId": [
        1654,
        1655,
        1656,
        1657
      ],
      "ResId": [
        1,
        1,
        1,
        1
      ]
    }
  },
  {
    "PigBankRow": {
      "ID": 13,
      "ActivityId": 20230101,
      "Type": 1,
      "ShopId": 10003,
      "BaseValue": 1200,
      "InitValue": 2400,
      "MaxValue": 4800,
      "LayerAdd": 50,
      "TimeLimit": 72,
      "TitleId": 1652,
      "DescId": [
        1654,
        1655,
        1656,
        1657
      ],
      "ResId": [
        1,
        1,
        1,
        1
      ]
    }
  },
  {
    "PigBankRow": {
      "ID": 14,
      "ActivityId": 20230101,
      "Type": 1,
      "ShopId": 10004,
      "BaseValue": 2500,
      "InitValue": 5000,
      "MaxValue": 10000,
      "LayerAdd": 100,
      "TimeLimit": 72,
      "TitleId": 1653,
      "DescId": [
        1654,
        1655,
        1656,
        1657
      ],
      "ResId": [
        1,
        1,
        1,
        1
      ]
    }
  },
  {
    "PigBankRow": {
      "ID": 15,
      "ActivityId": 20230306,
      "Type": 1,
      "ShopId": 10001,
      "BaseValue": 80,
      "InitValue": 160,
      "MaxValue": 320,
      "LayerAdd": 10,
      "TimeLimit": 24,
      "TitleId": 1790,
      "DescId": [
        1794,
        1795,
        1796,
        1797
      ],
      "ResId": [
        15,
        15,
        15,
        15
      ]
    }
  },
  {
    "PigBankRow": {
      "ID": 16,
      "ActivityId": 20230306,
      "Type": 1,
      "ShopId": 10002,
      "BaseValue": 500,
      "InitValue": 1000,
      "MaxValue": 2000,
      "LayerAdd": 25,
      "TimeLimit": 48,
      "TitleId": 1791,
      "DescId": [
        1794,
        1795,
        1796,
        1797
      ],
      "ResId": [
        16,
        16,
        16,
        16
      ]
    }
  },
  {
    "PigBankRow": {
      "ID": 17,
      "ActivityId": 20230306,
      "Type": 1,
      "ShopId": 10003,
      "BaseValue": 1200,
      "InitValue": 2400,
      "MaxValue": 4800,
      "LayerAdd": 50,
      "TimeLimit": 72,
      "TitleId": 1792,
      "DescId": [
        1794,
        1795,
        1796,
        1797
      ],
      "ResId": [
        17,
        17,
        17,
        17
      ]
    }
  },
  {
    "PigBankRow": {
      "ID": 18,
      "ActivityId": 20230306,
      "Type": 1,
      "ShopId": 10004,
      "BaseValue": 2500,
      "InitValue": 5000,
      "MaxValue": 10000,
      "LayerAdd": 100,
      "TimeLimit": 72,
      "TitleId": 1793,
      "DescId": [
        1794,
        1795,
        1796,
        1797
      ],
      "ResId": [
        18,
        18,
        18,
        18
      ]
    }
  },
  {
    "PigBankRow": {
      "ID": 19,
      "ActivityId": 20230409,
      "Type": 1,
      "ShopId": 10001,
      "BaseValue": 80,
      "InitValue": 160,
      "MaxValue": 320,
      "LayerAdd": 10,
      "TimeLimit": 24,
      "TitleId": 2710,
      "DescId": [
        2714,
        2715,
        2716,
        2717
      ],
      "ResId": [
        19,
        19,
        19,
        19
      ]
    }
  },
  {
    "PigBankRow": {
      "ID": 20,
      "ActivityId": 20230409,
      "Type": 1,
      "ShopId": 10002,
      "BaseValue": 500,
      "InitValue": 1000,
      "MaxValue": 2000,
      "LayerAdd": 25,
      "TimeLimit": 48,
      "TitleId": 2711,
      "DescId": [
        2714,
        2715,
        2716,
        2717
      ],
      "ResId": [
        20,
        20,
        20,
        20
      ]
    }
  },
  {
    "PigBankRow": {
      "ID": 21,
      "ActivityId": 20230409,
      "Type": 1,
      "ShopId": 10003,
      "BaseValue": 1200,
      "InitValue": 2400,
      "MaxValue": 4800,
      "LayerAdd": 50,
      "TimeLimit": 72,
      "TitleId": 2712,
      "DescId": [
        2714,
        2715,
        2716,
        2717
      ],
      "ResId": [
        21,
        21,
        21,
        21
      ]
    }
  },
  {
    "PigBankRow": {
      "ID": 22,
      "ActivityId": 20230409,
      "Type": 1,
      "ShopId": 10004,
      "BaseValue": 2500,
      "InitValue": 5000,
      "MaxValue": 10000,
      "LayerAdd": 100,
      "TimeLimit": 72,
      "TitleId": 2713,
      "DescId": [
        2714,
        2715,
        2716,
        2717
      ],
      "ResId": [
        22,
        22,
        22,
        22
      ]
    }
  },
  {
    "PigBankRow": {
      "ID": 23,
      "ActivityId": 20230503,
      "Type": 1,
      "ShopId": 10001,
      "BaseValue": 80,
      "InitValue": 160,
      "MaxValue": 320,
      "LayerAdd": 10,
      "TimeLimit": 24,
      "TitleId": 2891,
      "DescId": [
        2895,
        2896,
        2897,
        2898
      ],
      "ResId": [
        23,
        23,
        23,
        23
      ]
    }
  },
  {
    "PigBankRow": {
      "ID": 24,
      "ActivityId": 20230503,
      "Type": 1,
      "ShopId": 10002,
      "BaseValue": 500,
      "InitValue": 1000,
      "MaxValue": 2000,
      "LayerAdd": 25,
      "TimeLimit": 48,
      "TitleId": 2892,
      "DescId": [
        2895,
        2896,
        2897,
        2898
      ],
      "ResId": [
        24,
        24,
        24,
        24
      ]
    }
  },
  {
    "PigBankRow": {
      "ID": 25,
      "ActivityId": 20230503,
      "Type": 1,
      "ShopId": 10003,
      "BaseValue": 1200,
      "InitValue": 2400,
      "MaxValue": 4800,
      "LayerAdd": 50,
      "TimeLimit": 72,
      "TitleId": 2893,
      "DescId": [
        2895,
        2896,
        2897,
        2898
      ],
      "ResId": [
        25,
        25,
        25,
        25
      ]
    }
  },
  {
    "PigBankRow": {
      "ID": 26,
      "ActivityId": 20230503,
      "Type": 1,
      "ShopId": 10004,
      "BaseValue": 2500,
      "InitValue": 5000,
      "MaxValue": 10000,
      "LayerAdd": 100,
      "TimeLimit": 72,
      "TitleId": 2894,
      "DescId": [
        2895,
        2896,
        2897,
        2898
      ],
      "ResId": [
        26,
        26,
        26,
        26
      ]
    }
  },
  {
    "PigBankRow": {
      "ID": 27,
      "ActivityId": 20230615,
      "Type": 1,
      "ShopId": 10001,
      "BaseValue": 80,
      "InitValue": 160,
      "MaxValue": 320,
      "LayerAdd": 10,
      "TimeLimit": 24,
      "TitleId": 3133,
      "DescId": [
        3137,
        3138,
        3139,
        3140
      ],
      "ResId": [
        27,
        27,
        27,
        27
      ]
    }
  },
  {
    "PigBankRow": {
      "ID": 28,
      "ActivityId": 20230615,
      "Type": 1,
      "ShopId": 10002,
      "BaseValue": 500,
      "InitValue": 1000,
      "MaxValue": 2000,
      "LayerAdd": 25,
      "TimeLimit": 48,
      "TitleId": 3134,
      "DescId": [
        3137,
        3138,
        3139,
        3140
      ],
      "ResId": [
        28,
        28,
        28,
        28
      ]
    }
  },
  {
    "PigBankRow": {
      "ID": 29,
      "ActivityId": 20230615,
      "Type": 1,
      "ShopId": 10003,
      "BaseValue": 1200,
      "InitValue": 2400,
      "MaxValue": 4800,
      "LayerAdd": 50,
      "TimeLimit": 72,
      "TitleId": 3135,
      "DescId": [
        3137,
        3138,
        3139,
        3140
      ],
      "ResId": [
        29,
        29,
        29,
        29
      ]
    }
  },
  {
    "PigBankRow": {
      "ID": 30,
      "ActivityId": 20230615,
      "Type": 1,
      "ShopId": 10004,
      "BaseValue": 2500,
      "InitValue": 5000,
      "MaxValue": 10000,
      "LayerAdd": 100,
      "TimeLimit": 72,
      "TitleId": 3136,
      "DescId": [
        3137,
        3138,
        3139,
        3140
      ],
      "ResId": [
        30,
        30,
        30,
        30
      ]
    }
  },
  {
    "PigBankRow": {
      "ID": 31,
      "ActivityId": 20230716,
      "Type": 1,
      "ShopId": 10001,
      "BaseValue": 80,
      "InitValue": 160,
      "MaxValue": 320,
      "LayerAdd": 10,
      "TimeLimit": 24,
      "TitleId": 3271,
      "DescId": [
        3275,
        3276,
        3277,
        3278
      ],
      "ResId": [
        31,
        31,
        31,
        31
      ]
    }
  },
  {
    "PigBankRow": {
      "ID": 32,
      "ActivityId": 20230716,
      "Type": 1,
      "ShopId": 10002,
      "BaseValue": 500,
      "InitValue": 1000,
      "MaxValue": 2000,
      "LayerAdd": 50,
      "TimeLimit": 24,
      "TitleId": 3272,
      "DescId": [
        3275,
        3276,
        3277,
        3278
      ],
      "ResId": [
        32,
        32,
        32,
        32
      ]
    }
  },
  {
    "PigBankRow": {
      "ID": 33,
      "ActivityId": 20230716,
      "Type": 1,
      "ShopId": 10004,
      "BaseValue": 2500,
      "InitValue": 5000,
      "MaxValue": 10000,
      "LayerAdd": 250,
      "TimeLimit": 24,
      "TitleId": 3273,
      "DescId": [
        3275,
        3276,
        3277,
        3278
      ],
      "ResId": [
        33,
        33,
        33,
        33
      ]
    }
  },
  {
    "PigBankRow": {
      "ID": 34,
      "ActivityId": 20230716,
      "Type": 1,
      "ShopId": 10005,
      "BaseValue": 6500,
      "InitValue": 13000,
      "MaxValue": 26000,
      "LayerAdd": 650,
      "TimeLimit": 48,
      "TitleId": 3274,
      "DescId": [
        3275,
        3276,
        3277,
        3278
      ],
      "ResId": [
        34,
        34,
        34,
        34
      ]
    }
  },
  {
    "PigBankRow": {
      "ID": 35,
      "ActivityId": 20230808,
      "Type": 1,
      "ShopId": 10001,
      "BaseValue": 80,
      "InitValue": 160,
      "MaxValue": 320,
      "LayerAdd": 10,
      "TimeLimit": 24,
      "TitleId": 3416,
      "DescId": [
        3422,
        3423,
        3424,
        3425
      ],
      "ResId": [
        35,
        35,
        35,
        35
      ]
    }
  },
  {
    "PigBankRow": {
      "ID": 36,
      "ActivityId": 20230808,
      "Type": 1,
      "ShopId": 10002,
      "BaseValue": 500,
      "InitValue": 1000,
      "MaxValue": 2000,
      "LayerAdd": 50,
      "TimeLimit": 24,
      "TitleId": 3417,
      "DescId": [
        3422,
        3423,
        3424,
        3425
      ],
      "ResId": [
        36,
        36,
        36,
        36
      ]
    }
  },
  {
    "PigBankRow": {
      "ID": 37,
      "ActivityId": 20230808,
      "Type": 1,
      "ShopId": 10003,
      "BaseValue": 1200,
      "InitValue": 2400,
      "MaxValue": 4800,
      "LayerAdd": 120,
      "TimeLimit": 48,
      "TitleId": 3418,
      "DescId": [
        3422,
        3423,
        3424,
        3425
      ],
      "ResId": [
        37,
        37,
        37,
        37
      ]
    }
  },
  {
    "PigBankRow": {
      "ID": 38,
      "ActivityId": 20230808,
      "Type": 1,
      "ShopId": 10004,
      "BaseValue": 2500,
      "InitValue": 5000,
      "MaxValue": 10000,
      "LayerAdd": 250,
      "TimeLimit": 48,
      "TitleId": 3419,
      "DescId": [
        3422,
        3423,
        3424,
        3425
      ],
      "ResId": [
        38,
        38,
        38,
        38
      ]
    }
  },
  {
    "PigBankRow": {
      "ID": 39,
      "ActivityId": 20230808,
      "Type": 1,
      "ShopId": 10006,
      "BaseValue": 3750,
      "InitValue": 7500,
      "MaxValue": 15000,
      "LayerAdd": 375,
      "TimeLimit": 48,
      "TitleId": 3420,
      "DescId": [
        3422,
        3423,
        3424,
        3425
      ],
      "ResId": [
        39,
        39,
        39,
        39
      ]
    }
  },
  {
    "PigBankRow": {
      "ID": 40,
      "ActivityId": 20230808,
      "Type": 1,
      "ShopId": 10005,
      "BaseValue": 6500,
      "InitValue": 13000,
      "MaxValue": 26000,
      "LayerAdd": 650,
      "TimeLimit": 48,
      "TitleId": 3421,
      "DescId": [
        3422,
        3423,
        3424,
        3425
      ],
      "ResId": [
        40,
        40,
        40,
        40
      ]
    }
  },
  {
    "PigBankRow": {
      "ID": 41,
      "ActivityId": 20230824,
      "Type": 1,
      "ShopId": 10001,
      "BaseValue": 80,
      "InitValue": 160,
      "MaxValue": 320,
      "LayerAdd": 10,
      "TimeLimit": 24,
      "TitleId": 3484,
      "DescId": [
        1794,
        1795,
        1796,
        1797
      ],
      "ResId": [
        41,
        41,
        41,
        41
      ]
    }
  },
  {
    "PigBankRow": {
      "ID": 42,
      "ActivityId": 20230824,
      "Type": 1,
      "ShopId": 10002,
      "BaseValue": 500,
      "InitValue": 1000,
      "MaxValue": 2000,
      "LayerAdd": 50,
      "TimeLimit": 24,
      "TitleId": 3485,
      "DescId": [
        1794,
        1795,
        1796,
        1797
      ],
      "ResId": [
        42,
        42,
        42,
        42
      ]
    }
  },
  {
    "PigBankRow": {
      "ID": 43,
      "ActivityId": 20230824,
      "Type": 1,
      "ShopId": 10004,
      "BaseValue": 2500,
      "InitValue": 5000,
      "MaxValue": 10000,
      "LayerAdd": 250,
      "TimeLimit": 24,
      "TitleId": 3486,
      "DescId": [
        1794,
        1795,
        1796,
        1797
      ],
      "ResId": [
        43,
        43,
        43,
        43
      ]
    }
  },
  {
    "PigBankRow": {
      "ID": 44,
      "ActivityId": 20230824,
      "Type": 1,
      "ShopId": 10005,
      "BaseValue": 6500,
      "InitValue": 13000,
      "MaxValue": 26000,
      "LayerAdd": 650,
      "TimeLimit": 48,
      "TitleId": 3487,
      "DescId": [
        1794,
        1795,
        1796,
        1797
      ],
      "ResId": [
        44,
        44,
        44,
        44
      ]
    }
  },
  {
    "PigBankRow": {
      "ID": 45,
      "ActivityId": 20230911,
      "Type": 1,
      "ShopId": 10001,
      "BaseValue": 80,
      "InitValue": 160,
      "MaxValue": 320,
      "LayerAdd": 10,
      "TimeLimit": 24,
      "TitleId": 3492,
      "DescId": [
        3496,
        3497,
        3498,
        3499
      ],
      "ResId": [
        23,
        23,
        23,
        23
      ]
    }
  },
  {
    "PigBankRow": {
      "ID": 46,
      "ActivityId": 20230911,
      "Type": 1,
      "ShopId": 10002,
      "BaseValue": 500,
      "InitValue": 1000,
      "MaxValue": 2000,
      "LayerAdd": 50,
      "TimeLimit": 24,
      "TitleId": 3493,
      "DescId": [
        3496,
        3497,
        3498,
        3499
      ],
      "ResId": [
        24,
        24,
        24,
        24
      ]
    }
  },
  {
    "PigBankRow": {
      "ID": 47,
      "ActivityId": 20230911,
      "Type": 1,
      "ShopId": 10004,
      "BaseValue": 2500,
      "InitValue": 5000,
      "MaxValue": 10000,
      "LayerAdd": 250,
      "TimeLimit": 24,
      "TitleId": 3494,
      "DescId": [
        3496,
        3497,
        3498,
        3499
      ],
      "ResId": [
        25,
        25,
        25,
        25
      ]
    }
  },
  {
    "PigBankRow": {
      "ID": 48,
      "ActivityId": 20230911,
      "Type": 1,
      "ShopId": 10005,
      "BaseValue": 6500,
      "InitValue": 13000,
      "MaxValue": 26000,
      "LayerAdd": 650,
      "TimeLimit": 48,
      "TitleId": 3495,
      "DescId": [
        3496,
        3497,
        3498,
        3499
      ],
      "ResId": [
        26,
        26,
        26,
        26
      ]
    }
  },
  {
    "PigBankRow": {
      "ID": 49,
      "ActivityId": 20231009,
      "Type": 1,
      "ShopId": 10001,
      "BaseValue": 80,
      "InitValue": 160,
      "MaxValue": 320,
      "LayerAdd": 10,
      "TimeLimit": 24,
      "TitleId": 3938,
      "DescId": [
        3942,
        3943,
        3944,
        3945
      ],
      "ResId": [
        45,
        45,
        45,
        45
      ]
    }
  },
  {
    "PigBankRow": {
      "ID": 50,
      "ActivityId": 20231009,
      "Type": 1,
      "ShopId": 10002,
      "BaseValue": 500,
      "InitValue": 1000,
      "MaxValue": 2000,
      "LayerAdd": 50,
      "TimeLimit": 24,
      "TitleId": 3939,
      "DescId": [
        3942,
        3943,
        3944,
        3945
      ],
      "ResId": [
        46,
        46,
        46,
        46
      ]
    }
  },
  {
    "PigBankRow": {
      "ID": 51,
      "ActivityId": 20231009,
      "Type": 1,
      "ShopId": 10004,
      "BaseValue": 2500,
      "InitValue": 5000,
      "MaxValue": 10000,
      "LayerAdd": 250,
      "TimeLimit": 24,
      "TitleId": 3940,
      "DescId": [
        3942,
        3943,
        3944,
        3945
      ],
      "ResId": [
        47,
        47,
        47,
        47
      ]
    }
  },
  {
    "PigBankRow": {
      "ID": 52,
      "ActivityId": 20231009,
      "Type": 1,
      "ShopId": 10005,
      "BaseValue": 6500,
      "InitValue": 13000,
      "MaxValue": 26000,
      "LayerAdd": 650,
      "TimeLimit": 48,
      "TitleId": 3941,
      "DescId": [
        3942,
        3943,
        3944,
        3945
      ],
      "ResId": [
        48,
        48,
        48,
        48
      ]
    }
  },
  {
    "PigBankRow": {
      "ID": 53,
      "ActivityId": 20231113,
      "Type": 1,
      "ShopId": 10001,
      "BaseValue": 80,
      "InitValue": 160,
      "MaxValue": 320,
      "LayerAdd": 10,
      "TimeLimit": 24,
      "TitleId": 4283,
      "DescId": [
        4287,
        4288,
        4289,
        4290
      ],
      "ResId": [
        49,
        49,
        49,
        49
      ]
    }
  },
  {
    "PigBankRow": {
      "ID": 54,
      "ActivityId": 20231113,
      "Type": 1,
      "ShopId": 10002,
      "BaseValue": 500,
      "InitValue": 1000,
      "MaxValue": 2000,
      "LayerAdd": 50,
      "TimeLimit": 24,
      "TitleId": 4284,
      "DescId": [
        4287,
        4288,
        4289,
        4290
      ],
      "ResId": [
        50,
        50,
        50,
        50
      ]
    }
  },
  {
    "PigBankRow": {
      "ID": 55,
      "ActivityId": 20231113,
      "Type": 1,
      "ShopId": 10004,
      "BaseValue": 2500,
      "InitValue": 5000,
      "MaxValue": 10000,
      "LayerAdd": 250,
      "TimeLimit": 24,
      "TitleId": 4285,
      "DescId": [
        4287,
        4288,
        4289,
        4290
      ],
      "ResId": [
        51,
        51,
        51,
        51
      ]
    }
  },
  {
    "PigBankRow": {
      "ID": 56,
      "ActivityId": 20231113,
      "Type": 1,
      "ShopId": 10005,
      "BaseValue": 6500,
      "InitValue": 13000,
      "MaxValue": 26000,
      "LayerAdd": 650,
      "TimeLimit": 48,
      "TitleId": 4286,
      "DescId": [
        4287,
        4288,
        4289,
        4290
      ],
      "ResId": [
        52,
        52,
        52,
        52
      ]
    }
  },
  {
    "PigBankRow": {
      "ID": 57,
      "ActivityId": 20231219,
      "Type": 1,
      "ShopId": 10001,
      "BaseValue": 80,
      "InitValue": 160,
      "MaxValue": 320,
      "LayerAdd": 10,
      "TimeLimit": 24,
      "TitleId": 4392,
      "DescId": [
        4396,
        4397,
        4398,
        4399
      ],
      "ResId": [
        41,
        41,
        41,
        41
      ]
    }
  },
  {
    "PigBankRow": {
      "ID": 58,
      "ActivityId": 20231219,
      "Type": 1,
      "ShopId": 10002,
      "BaseValue": 500,
      "InitValue": 1000,
      "MaxValue": 2000,
      "LayerAdd": 50,
      "TimeLimit": 24,
      "TitleId": 4393,
      "DescId": [
        4396,
        4397,
        4398,
        4399
      ],
      "ResId": [
        42,
        42,
        42,
        42
      ]
    }
  },
  {
    "PigBankRow": {
      "ID": 59,
      "ActivityId": 20231219,
      "Type": 1,
      "ShopId": 10004,
      "BaseValue": 2500,
      "InitValue": 5000,
      "MaxValue": 10000,
      "LayerAdd": 250,
      "TimeLimit": 24,
      "TitleId": 4394,
      "DescId": [
        4396,
        4397,
        4398,
        4399
      ],
      "ResId": [
        43,
        43,
        43,
        43
      ]
    }
  },
  {
    "PigBankRow": {
      "ID": 60,
      "ActivityId": 20231219,
      "Type": 1,
      "ShopId": 10005,
      "BaseValue": 6500,
      "InitValue": 13000,
      "MaxValue": 26000,
      "LayerAdd": 650,
      "TimeLimit": 48,
      "TitleId": 4395,
      "DescId": [
        4396,
        4397,
        4398,
        4399
      ],
      "ResId": [
        44,
        44,
        44,
        44
      ]
    }
  },
  {
    "PigBankRow": {
      "ID": 61,
      "ActivityId": 20240210,
      "Type": 1,
      "ShopId": 10001,
      "BaseValue": 80,
      "InitValue": 160,
      "MaxValue": 320,
      "LayerAdd": 10,
      "TimeLimit": 24,
      "TitleId": 4473,
      "DescId": [
        4477,
        4478,
        4479,
        4480
      ],
      "ResId": [
        53,
        53,
        53,
        53
      ]
    }
  },
  {
    "PigBankRow": {
      "ID": 62,
      "ActivityId": 20240210,
      "Type": 1,
      "ShopId": 10002,
      "BaseValue": 500,
      "InitValue": 1000,
      "MaxValue": 2000,
      "LayerAdd": 50,
      "TimeLimit": 24,
      "TitleId": 4474,
      "DescId": [
        4477,
        4478,
        4479,
        4480
      ],
      "ResId": [
        54,
        54,
        54,
        54
      ]
    }
  },
  {
    "PigBankRow": {
      "ID": 63,
      "ActivityId": 20240210,
      "Type": 1,
      "ShopId": 10004,
      "BaseValue": 2500,
      "InitValue": 5000,
      "MaxValue": 10000,
      "LayerAdd": 250,
      "TimeLimit": 24,
      "TitleId": 4475,
      "DescId": [
        4477,
        4478,
        4479,
        4480
      ],
      "ResId": [
        55,
        55,
        55,
        55
      ]
    }
  },
  {
    "PigBankRow": {
      "ID": 64,
      "ActivityId": 20240210,
      "Type": 1,
      "ShopId": 10005,
      "BaseValue": 6500,
      "InitValue": 13000,
      "MaxValue": 26000,
      "LayerAdd": 650,
      "TimeLimit": 48,
      "TitleId": 4476,
      "DescId": [
        4477,
        4478,
        4479,
        4480
      ],
      "ResId": [
        56,
        56,
        56,
        56
      ]
    }
  },
  {
    "PigBankRow": {
      "ID": 65,
      "ActivityId": 20240304,
      "Type": 1,
      "ShopId": 10001,
      "BaseValue": 80,
      "InitValue": 160,
      "MaxValue": 320,
      "LayerAdd": 10,
      "TimeLimit": 24,
      "TitleId": 4597,
      "DescId": [
        4601,
        4602,
        4603,
        4604
      ],
      "ResId": [
        57,
        57,
        57,
        57
      ]
    }
  },
  {
    "PigBankRow": {
      "ID": 66,
      "ActivityId": 20240304,
      "Type": 1,
      "ShopId": 10002,
      "BaseValue": 500,
      "InitValue": 1000,
      "MaxValue": 2000,
      "LayerAdd": 50,
      "TimeLimit": 24,
      "TitleId": 4598,
      "DescId": [
        4601,
        4602,
        4603,
        4604
      ],
      "ResId": [
        58,
        58,
        58,
        58
      ]
    }
  },
  {
    "PigBankRow": {
      "ID": 67,
      "ActivityId": 20240304,
      "Type": 1,
      "ShopId": 10004,
      "BaseValue": 2500,
      "InitValue": 5000,
      "MaxValue": 10000,
      "LayerAdd": 250,
      "TimeLimit": 24,
      "TitleId": 4599,
      "DescId": [
        4601,
        4602,
        4603,
        4604
      ],
      "ResId": [
        59,
        59,
        59,
        59
      ]
    }
  },
  {
    "PigBankRow": {
      "ID": 68,
      "ActivityId": 20240304,
      "Type": 1,
      "ShopId": 10005,
      "BaseValue": 6500,
      "InitValue": 13000,
      "MaxValue": 26000,
      "LayerAdd": 650,
      "TimeLimit": 48,
      "TitleId": 4600,
      "DescId": [
        4601,
        4602,
        4603,
        4604
      ],
      "ResId": [
        60,
        60,
        60,
        60
      ]
    }
  },
  {
    "PigBankRow": {
      "ID": 69,
      "ActivityId": 20240410,
      "Type": 1,
      "ShopId": 10001,
      "BaseValue": 80,
      "InitValue": 160,
      "MaxValue": 320,
      "LayerAdd": 10,
      "TimeLimit": 24,
      "TitleId": 4798,
      "DescId": [
        4802,
        4803,
        4804,
        4805
      ],
      "ResId": [
        35,
        35,
        35,
        35
      ]
    }
  },
  {
    "PigBankRow": {
      "ID": 70,
      "ActivityId": 20240410,
      "Type": 1,
      "ShopId": 10002,
      "BaseValue": 500,
      "InitValue": 1000,
      "MaxValue": 2000,
      "LayerAdd": 50,
      "TimeLimit": 24,
      "TitleId": 4799,
      "DescId": [
        4802,
        4803,
        4804,
        4805
      ],
      "ResId": [
        36,
        36,
        36,
        36
      ]
    }
  },
  {
    "PigBankRow": {
      "ID": 71,
      "ActivityId": 20240410,
      "Type": 1,
      "ShopId": 10004,
      "BaseValue": 2500,
      "InitValue": 5000,
      "MaxValue": 10000,
      "LayerAdd": 250,
      "TimeLimit": 24,
      "TitleId": 4800,
      "DescId": [
        4802,
        4803,
        4804,
        4805
      ],
      "ResId": [
        37,
        37,
        37,
        37
      ]
    }
  },
  {
    "PigBankRow": {
      "ID": 72,
      "ActivityId": 20240410,
      "Type": 1,
      "ShopId": 10005,
      "BaseValue": 6500,
      "InitValue": 13000,
      "MaxValue": 26000,
      "LayerAdd": 650,
      "TimeLimit": 48,
      "TitleId": 4801,
      "DescId": [
        4802,
        4803,
        4804,
        4805
      ],
      "ResId": [
        38,
        38,
        38,
        38
      ]
    }
  },
  {
    "PigBankRow": {
      "ID": 73,
      "ActivityId": 20240410,
      "Type": 1,
      "ShopId": 10007,
      "BaseValue": 6500,
      "InitValue": 13000,
      "MaxValue": 26000,
      "LayerAdd": 650,
      "TimeLimit": 48,
      "TitleId": 4796,
      "DescId": [
        4802,
        4803,
        4804,
        4805
      ],
      "ResId": [
        39,
        39,
        39,
        39
      ]
    }
  },
  {
    "PigBankRow": {
      "ID": 74,
      "ActivityId": 20240410,
      "Type": 1,
      "ShopId": 10008,
      "BaseValue": 6500,
      "InitValue": 13000,
      "MaxValue": 26000,
      "LayerAdd": 650,
      "TimeLimit": 48,
      "TitleId": 4797,
      "DescId": [
        4802,
        4803,
        4804,
        4805
      ],
      "ResId": [
        40,
        40,
        40,
        40
      ]
    }
  },
  {
    "PigBankRow": {
      "ID": 75,
      "ActivityId": 20240414,
      "Type": 1,
      "ShopId": 10001,
      "BaseValue": 80,
      "InitValue": 160,
      "MaxValue": 320,
      "LayerAdd": 10,
      "TimeLimit": 24,
      "TitleId": 1790,
      "DescId": [
        1794,
        1795,
        1796,
        1797
      ],
      "ResId": [
        41,
        41,
        41,
        41
      ]
    }
  },
  {
    "PigBankRow": {
      "ID": 76,
      "ActivityId": 20240414,
      "Type": 1,
      "ShopId": 10002,
      "BaseValue": 500,
      "InitValue": 1000,
      "MaxValue": 2000,
      "LayerAdd": 50,
      "TimeLimit": 24,
      "TitleId": 1791,
      "DescId": [
        1794,
        1795,
        1796,
        1797
      ],
      "ResId": [
        42,
        42,
        42,
        42
      ]
    }
  },
  {
    "PigBankRow": {
      "ID": 77,
      "ActivityId": 20240414,
      "Type": 1,
      "ShopId": 10004,
      "BaseValue": 2500,
      "InitValue": 5000,
      "MaxValue": 10000,
      "LayerAdd": 250,
      "TimeLimit": 24,
      "TitleId": 1792,
      "DescId": [
        1794,
        1795,
        1796,
        1797
      ],
      "ResId": [
        43,
        43,
        43,
        43
      ]
    }
  },
  {
    "PigBankRow": {
      "ID": 78,
      "ActivityId": 20240414,
      "Type": 1,
      "ShopId": 10005,
      "BaseValue": 6500,
      "InitValue": 13000,
      "MaxValue": 26000,
      "LayerAdd": 650,
      "TimeLimit": 48,
      "TitleId": 1793,
      "DescId": [
        1794,
        1795,
        1796,
        1797
      ],
      "ResId": [
        44,
        44,
        44,
        44
      ]
    }
  },
  {
    "PigBankRow": {
      "ID": 79,
      "ActivityId": 20240516,
      "Type": 1,
      "ShopId": 10001,
      "BaseValue": 80,
      "InitValue": 160,
      "MaxValue": 320,
      "LayerAdd": 10,
      "TimeLimit": 24,
      "TitleId": 3271,
      "DescId": [
        3275,
        3276,
        3277,
        3278
      ],
      "ResId": [
        31,
        31,
        31,
        31
      ]
    }
  },
  {
    "PigBankRow": {
      "ID": 80,
      "ActivityId": 20240516,
      "Type": 1,
      "ShopId": 10002,
      "BaseValue": 500,
      "InitValue": 1000,
      "MaxValue": 2000,
      "LayerAdd": 50,
      "TimeLimit": 24,
      "TitleId": 3272,
      "DescId": [
        3275,
        3276,
        3277,
        3278
      ],
      "ResId": [
        32,
        32,
        32,
        32
      ]
    }
  },
  {
    "PigBankRow": {
      "ID": 81,
      "ActivityId": 20240516,
      "Type": 1,
      "ShopId": 10004,
      "BaseValue": 2500,
      "InitValue": 5000,
      "MaxValue": 10000,
      "LayerAdd": 250,
      "TimeLimit": 24,
      "TitleId": 3273,
      "DescId": [
        3275,
        3276,
        3277,
        3278
      ],
      "ResId": [
        33,
        33,
        33,
        33
      ]
    }
  },
  {
    "PigBankRow": {
      "ID": 82,
      "ActivityId": 20240516,
      "Type": 1,
      "ShopId": 10005,
      "BaseValue": 6500,
      "InitValue": 13000,
      "MaxValue": 26000,
      "LayerAdd": 650,
      "TimeLimit": 48,
      "TitleId": 3274,
      "DescId": [
        3275,
        3276,
        3277,
        3278
      ],
      "ResId": [
        34,
        34,
        34,
        34
      ]
    }
  },
  {
    "PigBankRow": {
      "ID": 83,
      "ActivityId": 20240612,
      "Type": 1,
      "ShopId": 10001,
      "BaseValue": 80,
      "InitValue": 160,
      "MaxValue": 320,
      "LayerAdd": 10,
      "TimeLimit": 24,
      "TitleId": 3271,
      "DescId": [
        3275,
        3276,
        3277,
        3278
      ],
      "ResId": [
        27,
        27,
        27,
        27
      ]
    }
  },
  {
    "PigBankRow": {
      "ID": 84,
      "ActivityId": 20240612,
      "Type": 1,
      "ShopId": 10002,
      "BaseValue": 500,
      "InitValue": 1000,
      "MaxValue": 2000,
      "LayerAdd": 50,
      "TimeLimit": 24,
      "TitleId": 3272,
      "DescId": [
        3275,
        3276,
        3277,
        3278
      ],
      "ResId": [
        28,
        28,
        28,
        28
      ]
    }
  },
  {
    "PigBankRow": {
      "ID": 85,
      "ActivityId": 20240612,
      "Type": 1,
      "ShopId": 10004,
      "BaseValue": 2500,
      "InitValue": 5000,
      "MaxValue": 10000,
      "LayerAdd": 250,
      "TimeLimit": 24,
      "TitleId": 3273,
      "DescId": [
        3275,
        3276,
        3277,
        3278
      ],
      "ResId": [
        29,
        29,
        29,
        29
      ]
    }
  },
  {
    "PigBankRow": {
      "ID": 86,
      "ActivityId": 20240612,
      "Type": 1,
      "ShopId": 10005,
      "BaseValue": 6500,
      "InitValue": 13000,
      "MaxValue": 26000,
      "LayerAdd": 650,
      "TimeLimit": 48,
      "TitleId": 3274,
      "DescId": [
        3275,
        3276,
        3277,
        3278
      ],
      "ResId": [
        30,
        30,
        30,
        30
      ]
    }
  },
  {
    "PigBankRow": {
      "ID": 87,
      "ActivityId": 20240612,
      "Type": 1,
      "ShopId": 10007,
      "BaseValue": 6500,
      "InitValue": 13000,
      "MaxValue": 26000,
      "LayerAdd": 650,
      "TimeLimit": 48,
      "TitleId": 4745,
      "DescId": [
        3275,
        3276,
        3277,
        3278
      ],
      "ResId": [
        30,
        30,
        30,
        30
      ]
    }
  },
  {
    "PigBankRow": {
      "ID": 88,
      "ActivityId": 20240612,
      "Type": 1,
      "ShopId": 10008,
      "BaseValue": 6500,
      "InitValue": 13000,
      "MaxValue": 26000,
      "LayerAdd": 650,
      "TimeLimit": 48,
      "TitleId": 4746,
      "DescId": [
        3275,
        3276,
        3277,
        3278
      ],
      "ResId": [
        30,
        30,
        30,
        30
      ]
    }
  },
  {
    "PigBankRow": {
      "ID": 89,
      "ActivityId": 20240716,
      "Type": 1,
      "ShopId": 10001,
      "BaseValue": 80,
      "InitValue": 160,
      "MaxValue": 320,
      "LayerAdd": 10,
      "TimeLimit": 24,
      "TitleId": 3271,
      "DescId": [
        3275,
        3276,
        3277,
        3278
      ],
      "ResId": [
        27,
        27,
        27,
        27
      ]
    }
  },
  {
    "PigBankRow": {
      "ID": 90,
      "ActivityId": 20240716,
      "Type": 1,
      "ShopId": 10002,
      "BaseValue": 500,
      "InitValue": 1000,
      "MaxValue": 2000,
      "LayerAdd": 50,
      "TimeLimit": 24,
      "TitleId": 3272,
      "DescId": [
        3275,
        3276,
        3277,
        3278
      ],
      "ResId": [
        28,
        28,
        28,
        28
      ]
    }
  },
  {
    "PigBankRow": {
      "ID": 91,
      "ActivityId": 20240716,
      "Type": 1,
      "ShopId": 10004,
      "BaseValue": 2500,
      "InitValue": 5000,
      "MaxValue": 10000,
      "LayerAdd": 250,
      "TimeLimit": 24,
      "TitleId": 3273,
      "DescId": [
        3275,
        3276,
        3277,
        3278
      ],
      "ResId": [
        29,
        29,
        29,
        29
      ]
    }
  },
  {
    "PigBankRow": {
      "ID": 92,
      "ActivityId": 20240716,
      "Type": 1,
      "ShopId": 10005,
      "BaseValue": 6500,
      "InitValue": 13000,
      "MaxValue": 26000,
      "LayerAdd": 650,
      "TimeLimit": 48,
      "TitleId": 3274,
      "DescId": [
        3275,
        3276,
        3277,
        3278
      ],
      "ResId": [
        30,
        30,
        30,
        30
      ]
    }
  },
  {
    "PigBankRow": {
      "ID": 93,
      "ActivityId": 20240716,
      "Type": 1,
      "ShopId": 10007,
      "BaseValue": 6500,
      "InitValue": 13000,
      "MaxValue": 26000,
      "LayerAdd": 650,
      "TimeLimit": 48,
      "TitleId": 4745,
      "DescId": [
        3275,
        3276,
        3277,
        3278
      ],
      "ResId": [
        30,
        30,
        30,
        30
      ]
    }
  },
  {
    "PigBankRow": {
      "ID": 94,
      "ActivityId": 20240716,
      "Type": 1,
      "ShopId": 10008,
      "BaseValue": 6500,
      "InitValue": 13000,
      "MaxValue": 26000,
      "LayerAdd": 650,
      "TimeLimit": 48,
      "TitleId": 4746,
      "DescId": [
        3275,
        3276,
        3277,
        3278
      ],
      "ResId": [
        30,
        30,
        30,
        30
      ]
    }
  },
  {
    "PigBankRow": {
      "ID": 95,
      "ActivityId": 20240822,
      "Type": 1,
      "ShopId": 10001,
      "BaseValue": 80,
      "InitValue": 160,
      "MaxValue": 320,
      "LayerAdd": 10,
      "TimeLimit": 24,
      "TitleId": 3271,
      "DescId": [
        3275,
        3276,
        3277,
        3278
      ],
      "ResId": [
        27,
        27,
        27,
        27
      ]
    }
  },
  {
    "PigBankRow": {
      "ID": 96,
      "ActivityId": 20240822,
      "Type": 1,
      "ShopId": 10002,
      "BaseValue": 500,
      "InitValue": 1000,
      "MaxValue": 2000,
      "LayerAdd": 50,
      "TimeLimit": 24,
      "TitleId": 3272,
      "DescId": [
        3275,
        3276,
        3277,
        3278
      ],
      "ResId": [
        28,
        28,
        28,
        28
      ]
    }
  },
  {
    "PigBankRow": {
      "ID": 97,
      "ActivityId": 20240822,
      "Type": 1,
      "ShopId": 10004,
      "BaseValue": 2500,
      "InitValue": 5000,
      "MaxValue": 10000,
      "LayerAdd": 250,
      "TimeLimit": 24,
      "TitleId": 3273,
      "DescId": [
        3275,
        3276,
        3277,
        3278
      ],
      "ResId": [
        29,
        29,
        29,
        29
      ]
    }
  },
  {
    "PigBankRow": {
      "ID": 98,
      "ActivityId": 20240822,
      "Type": 1,
      "ShopId": 10005,
      "BaseValue": 6500,
      "InitValue": 13000,
      "MaxValue": 26000,
      "LayerAdd": 650,
      "TimeLimit": 48,
      "TitleId": 3274,
      "DescId": [
        3275,
        3276,
        3277,
        3278
      ],
      "ResId": [
        30,
        30,
        30,
        30
      ]
    }
  },
  {
    "PigBankRow": {
      "ID": 99,
      "ActivityId": 20240822,
      "Type": 1,
      "ShopId": 10007,
      "BaseValue": 6500,
      "InitValue": 13000,
      "MaxValue": 26000,
      "LayerAdd": 650,
      "TimeLimit": 48,
      "TitleId": 4745,
      "DescId": [
        3275,
        3276,
        3277,
        3278
      ],
      "ResId": [
        30,
        30,
        30,
        30
      ]
    }
  },
  {
    "PigBankRow": {
      "ID": 100,
      "ActivityId": 20240822,
      "Type": 1,
      "ShopId": 10008,
      "BaseValue": 6500,
      "InitValue": 13000,
      "MaxValue": 26000,
      "LayerAdd": 650,
      "TimeLimit": 48,
      "TitleId": 4746,
      "DescId": [
        3275,
        3276,
        3277,
        3278
      ],
      "ResId": [
        30,
        30,
        30,
        30
      ]
    }
  },
  {
    "PigBankRow": {
      "ID": 101,
      "ActivityId": 20240913,
      "Type": 1,
      "ShopId": 10001,
      "BaseValue": 80,
      "InitValue": 160,
      "MaxValue": 320,
      "LayerAdd": 10,
      "TimeLimit": 24,
      "TitleId": 3492,
      "DescId": [
        3496,
        3497,
        3498,
        3499
      ],
      "ResId": [
        23,
        23,
        23,
        23
      ]
    }
  },
  {
    "PigBankRow": {
      "ID": 102,
      "ActivityId": 20240913,
      "Type": 1,
      "ShopId": 10002,
      "BaseValue": 500,
      "InitValue": 1000,
      "MaxValue": 2000,
      "LayerAdd": 50,
      "TimeLimit": 24,
      "TitleId": 3493,
      "DescId": [
        3496,
        3497,
        3498,
        3499
      ],
      "ResId": [
        24,
        24,
        24,
        24
      ]
    }
  },
  {
    "PigBankRow": {
      "ID": 103,
      "ActivityId": 20240913,
      "Type": 1,
      "ShopId": 10004,
      "BaseValue": 2500,
      "InitValue": 5000,
      "MaxValue": 10000,
      "LayerAdd": 250,
      "TimeLimit": 24,
      "TitleId": 3494,
      "DescId": [
        3496,
        3497,
        3498,
        3499
      ],
      "ResId": [
        25,
        25,
        25,
        25
      ]
    }
  },
  {
    "PigBankRow": {
      "ID": 104,
      "ActivityId": 20240913,
      "Type": 1,
      "ShopId": 10005,
      "BaseValue": 6500,
      "InitValue": 13000,
      "MaxValue": 26000,
      "LayerAdd": 650,
      "TimeLimit": 48,
      "TitleId": 3495,
      "DescId": [
        3496,
        3497,
        3498,
        3499
      ],
      "ResId": [
        26,
        26,
        26,
        26
      ]
    }
  },
  {
    "PigBankRow": {
      "ID": 105,
      "ActivityId": 20240913,
      "Type": 1,
      "ShopId": 10007,
      "BaseValue": 6500,
      "InitValue": 13000,
      "MaxValue": 26000,
      "LayerAdd": 650,
      "TimeLimit": 48,
      "TitleId": 4626,
      "DescId": [
        3496,
        3497,
        3498,
        3499
      ],
      "ResId": [
        26,
        26,
        26,
        26
      ]
    }
  },
  {
    "PigBankRow": {
      "ID": 106,
      "ActivityId": 20240913,
      "Type": 1,
      "ShopId": 10008,
      "BaseValue": 6500,
      "InitValue": 13000,
      "MaxValue": 26000,
      "LayerAdd": 650,
      "TimeLimit": 48,
      "TitleId": 4627,
      "DescId": [
        3496,
        3497,
        3498,
        3499
      ],
      "ResId": [
        26,
        26,
        26,
        26
      ]
    }
  },
  {
    "PigBankRow": {
      "ID": 107,
      "ActivityId": 20241013,
      "Type": 1,
      "ShopId": 10001,
      "BaseValue": 80,
      "InitValue": 160,
      "MaxValue": 320,
      "LayerAdd": 10,
      "TimeLimit": 24,
      "TitleId": 4597,
      "DescId": [
        4601,
        4602,
        4603,
        4604
      ],
      "ResId": [
        57,
        57,
        57,
        57
      ]
    }
  },
  {
    "PigBankRow": {
      "ID": 108,
      "ActivityId": 20241013,
      "Type": 1,
      "ShopId": 10002,
      "BaseValue": 500,
      "InitValue": 1000,
      "MaxValue": 2000,
      "LayerAdd": 50,
      "TimeLimit": 24,
      "TitleId": 4598,
      "DescId": [
        4601,
        4602,
        4603,
        4604
      ],
      "ResId": [
        58,
        58,
        58,
        58
      ]
    }
  },
  {
    "PigBankRow": {
      "ID": 109,
      "ActivityId": 20241013,
      "Type": 1,
      "ShopId": 10004,
      "BaseValue": 2500,
      "InitValue": 5000,
      "MaxValue": 10000,
      "LayerAdd": 250,
      "TimeLimit": 24,
      "TitleId": 4599,
      "DescId": [
        4601,
        4602,
        4603,
        4604
      ],
      "ResId": [
        59,
        59,
        59,
        59
      ]
    }
  },
  {
    "PigBankRow": {
      "ID": 110,
      "ActivityId": 20241013,
      "Type": 1,
      "ShopId": 10005,
      "BaseValue": 6500,
      "InitValue": 13000,
      "MaxValue": 26000,
      "LayerAdd": 650,
      "TimeLimit": 48,
      "TitleId": 4600,
      "DescId": [
        4601,
        4602,
        4603,
        4604
      ],
      "ResId": [
        60,
        60,
        60,
        60
      ]
    }
  },
  {
    "PigBankRow": {
      "ID": 111,
      "ActivityId": 20241013,
      "Type": 1,
      "ShopId": 10007,
      "BaseValue": 6500,
      "InitValue": 13000,
      "MaxValue": 26000,
      "LayerAdd": 650,
      "TimeLimit": 48,
      "TitleId": 4783,
      "DescId": [
        4601,
        4602,
        4603,
        4604
      ],
      "ResId": [
        60,
        60,
        60,
        60
      ]
    }
  },
  {
    "PigBankRow": {
      "ID": 112,
      "ActivityId": 20241013,
      "Type": 1,
      "ShopId": 10008,
      "BaseValue": 6500,
      "InitValue": 13000,
      "MaxValue": 26000,
      "LayerAdd": 650,
      "TimeLimit": 48,
      "TitleId": 4784,
      "DescId": [
        4601,
        4602,
        4603,
        4604
      ],
      "ResId": [
        60,
        60,
        60,
        60
      ]
    }
  },
  {
    "PigBankRow": {
      "ID": 113,
      "ActivityId": 20241113,
      "Type": 1,
      "ShopId": 10001,
      "BaseValue": 80,
      "InitValue": 160,
      "MaxValue": 320,
      "LayerAdd": 10,
      "TimeLimit": 24,
      "TitleId": 3938,
      "DescId": [
        3942,
        3943,
        3944,
        3945
      ],
      "ResId": [
        45,
        45,
        45,
        45
      ]
    }
  },
  {
    "PigBankRow": {
      "ID": 114,
      "ActivityId": 20241113,
      "Type": 1,
      "ShopId": 10002,
      "BaseValue": 500,
      "InitValue": 1000,
      "MaxValue": 2000,
      "LayerAdd": 50,
      "TimeLimit": 24,
      "TitleId": 3939,
      "DescId": [
        3942,
        3943,
        3944,
        3945
      ],
      "ResId": [
        46,
        46,
        46,
        46
      ]
    }
  },
  {
    "PigBankRow": {
      "ID": 115,
      "ActivityId": 20241113,
      "Type": 1,
      "ShopId": 10004,
      "BaseValue": 2500,
      "InitValue": 5000,
      "MaxValue": 10000,
      "LayerAdd": 250,
      "TimeLimit": 24,
      "TitleId": 3940,
      "DescId": [
        3942,
        3943,
        3944,
        3945
      ],
      "ResId": [
        47,
        47,
        47,
        47
      ]
    }
  },
  {
    "PigBankRow": {
      "ID": 116,
      "ActivityId": 20241113,
      "Type": 1,
      "ShopId": 10005,
      "BaseValue": 6500,
      "InitValue": 13000,
      "MaxValue": 26000,
      "LayerAdd": 650,
      "TimeLimit": 48,
      "TitleId": 3941,
      "DescId": [
        3942,
        3943,
        3944,
        3945
      ],
      "ResId": [
        48,
        48,
        48,
        48
      ]
    }
  },
  {
    "PigBankRow": {
      "ID": 117,
      "ActivityId": 20241113,
      "Type": 1,
      "ShopId": 10007,
      "BaseValue": 6500,
      "InitValue": 13000,
      "MaxValue": 26000,
      "LayerAdd": 650,
      "TimeLimit": 48,
      "TitleId": 4862,
      "DescId": [
        3942,
        3943,
        3944,
        3945
      ],
      "ResId": [
        48,
        48,
        48,
        48
      ]
    }
  },
  {
    "PigBankRow": {
      "ID": 118,
      "ActivityId": 20241113,
      "Type": 1,
      "ShopId": 10008,
      "BaseValue": 6500,
      "InitValue": 13000,
      "MaxValue": 26000,
      "LayerAdd": 650,
      "TimeLimit": 48,
      "TitleId": 4863,
      "DescId": [
        3942,
        3943,
        3944,
        3945
      ],
      "ResId": [
        48,
        48,
        48,
        48
      ]
    }
  },
  {
    "PigBankRow": {
      "ID": 119,
      "ActivityId": 20241213,
      "Type": 1,
      "ShopId": 10001,
      "BaseValue": 80,
      "InitValue": 160,
      "MaxValue": 320,
      "LayerAdd": 10,
      "TimeLimit": 24,
      "TitleId": 3492,
      "DescId": [
        3496,
        3497,
        3498,
        3499
      ],
      "ResId": [
        23,
        23,
        23,
        23
      ]
    }
  },
  {
    "PigBankRow": {
      "ID": 120,
      "ActivityId": 20241213,
      "Type": 1,
      "ShopId": 10002,
      "BaseValue": 500,
      "InitValue": 1000,
      "MaxValue": 2000,
      "LayerAdd": 50,
      "TimeLimit": 24,
      "TitleId": 3493,
      "DescId": [
        3496,
        3497,
        3498,
        3499
      ],
      "ResId": [
        24,
        24,
        24,
        24
      ]
    }
  },
  {
    "PigBankRow": {
      "ID": 121,
      "ActivityId": 20241213,
      "Type": 1,
      "ShopId": 10004,
      "BaseValue": 2500,
      "InitValue": 5000,
      "MaxValue": 10000,
      "LayerAdd": 250,
      "TimeLimit": 24,
      "TitleId": 3494,
      "DescId": [
        3496,
        3497,
        3498,
        3499
      ],
      "ResId": [
        25,
        25,
        25,
        25
      ]
    }
  },
  {
    "PigBankRow": {
      "ID": 122,
      "ActivityId": 20241213,
      "Type": 1,
      "ShopId": 10005,
      "BaseValue": 6500,
      "InitValue": 13000,
      "MaxValue": 26000,
      "LayerAdd": 650,
      "TimeLimit": 48,
      "TitleId": 3495,
      "DescId": [
        3496,
        3497,
        3498,
        3499
      ],
      "ResId": [
        26,
        26,
        26,
        26
      ]
    }
  },
  {
    "PigBankRow": {
      "ID": 123,
      "ActivityId": 20241213,
      "Type": 1,
      "ShopId": 10007,
      "BaseValue": 6500,
      "InitValue": 13000,
      "MaxValue": 26000,
      "LayerAdd": 650,
      "TimeLimit": 48,
      "TitleId": 4626,
      "DescId": [
        3496,
        3497,
        3498,
        3499
      ],
      "ResId": [
        26,
        26,
        26,
        26
      ]
    }
  },
  {
    "PigBankRow": {
      "ID": 124,
      "ActivityId": 20241213,
      "Type": 1,
      "ShopId": 10008,
      "BaseValue": 6500,
      "InitValue": 13000,
      "MaxValue": 26000,
      "LayerAdd": 650,
      "TimeLimit": 48,
      "TitleId": 4627,
      "DescId": [
        3496,
        3497,
        3498,
        3499
      ],
      "ResId": [
        26,
        26,
        26,
        26
      ]
    }
  }
]